selenium_cookies/__init__.py
selenium_cookies/tests/__init__.py
selenium_cookies/tests/test_module.py
selenium_cookies-0.0.4.dist-info/LICENSE
selenium_cookies-0.0.4.dist-info/METADATA
selenium_cookies-0.0.4.dist-info/WHEEL
selenium_cookies-0.0.4.dist-info/top_level.txt
selenium_cookies-0.0.4.dist-info/RECORD
