Metadata-Version: 2.1
Name: selenium-cookies
Version: 0.0.4
Summary: Cookie handling for selenium webdrivers.
Home-page: https://github.com/adamhb123/selenium_cookies
Author: Adam Brewer
Author-email: adamhb321@gmail.com
License: UNKNOWN
Platform: UNKNOWN
Classifier: Programming Language :: Python :: 3
Classifier: License :: OSI Approved :: MIT License
Classifier: Operating System :: Microsoft :: Windows
Classifier: Operating System :: POSIX :: Linux
Requires-Python: >=3.4
Requires-Dist: selenium
